z3c.recipe.i18n-2.1-py3.11-nspkg.pth
z3c/recipe/i18n/README.rst
z3c/recipe/i18n/__init__.py
z3c/recipe/i18n/i18n.py
z3c/recipe/i18n/i18ncompile.py
z3c/recipe/i18n/i18nextract.py
z3c/recipe/i18n/i18nmergeall.py
z3c/recipe/i18n/i18nstats.py
z3c/recipe/i18n/testing.zcml
z3c/recipe/i18n/tests.py
z3c.recipe.i18n-2.1.dist-info/LICENSE.txt
z3c.recipe.i18n-2.1.dist-info/METADATA
z3c.recipe.i18n-2.1.dist-info/WHEEL
z3c.recipe.i18n-2.1.dist-info/entry_points.txt
z3c.recipe.i18n-2.1.dist-info/namespace_packages.txt
z3c.recipe.i18n-2.1.dist-info/top_level.txt
z3c.recipe.i18n-2.1.dist-info/RECORD
