Metadata-Version: 2.1
Name: z3c.recipe.i18n
Version: 2.1
Summary: Zope3 egg based i18n locales extraction recipes
Home-page: https://github.com/zopefoundation/z3c.recipe.i18n
Author: Roger Ineichen and the Zope Community
Author-email: zope-dev@zope.dev
License: ZPL 2.1
Keywords: zope3 z3c i18n locales extraction recipe
Classifier: Development Status :: 5 - Production/Stable
Classifier: Environment :: Web Environment
Classifier: Intended Audience :: Developers
Classifier: License :: OSI Approved :: Zope Public License
Classifier: Programming Language :: Python
Classifier: Natural Language :: English
Classifier: Operating System :: OS Independent
Classifier: Topic :: Internet :: WWW/HTTP
Classifier: Programming Language :: Python
Classifier: Programming Language :: Python :: 3
Classifier: Programming Language :: Python :: 3.8
Classifier: Programming Language :: Python :: 3.9
Classifier: Programming Language :: Python :: 3.10
Classifier: Programming Language :: Python :: 3.11
Classifier: Programming Language :: Python :: 3.12
Classifier: Programming Language :: Python :: 3.13
Classifier: Programming Language :: Python :: Implementation :: CPython
Classifier: Programming Language :: Python :: Implementation :: PyPy
Classifier: Framework :: Buildout
Requires-Python: >=3.8
License-File: LICENSE.txt
Requires-Dist: setuptools
Requires-Dist: zc.buildout>=2.0.0
Requires-Dist: zc.recipe.egg
Requires-Dist: zope.app.locales[extract]>=4.1
Provides-Extra: test
Requires-Dist: zope.component; extra == "test"
Requires-Dist: zope.configuration; extra == "test"
Requires-Dist: zope.event; extra == "test"
Requires-Dist: zope.i18nmessageid; extra == "test"
Requires-Dist: zope.interface; extra == "test"
Requires-Dist: zope.location; extra == "test"
Requires-Dist: zope.proxy; extra == "test"
Requires-Dist: zope.schema; extra == "test"
Requires-Dist: zope.security; extra == "test"
Requires-Dist: zope.tal; extra == "test"
Requires-Dist: zope.testing; extra == "test"
Requires-Dist: zope.testrunner; extra == "test"
